odoo/addons/fieldservice_maintenance/README.rst
odoo/addons/fieldservice_maintenance/__init__.py
odoo/addons/fieldservice_maintenance/__manifest__.py
odoo/addons/fieldservice_maintenance/hooks.py
odoo/addons/fieldservice_maintenance/data/fsm_order_type.xml
odoo/addons/fieldservice_maintenance/i18n/de.po
odoo/addons/fieldservice_maintenance/i18n/es_CL.po
odoo/addons/fieldservice_maintenance/i18n/fieldservice_maintenance.pot
odoo/addons/fieldservice_maintenance/i18n/pt_BR.po
odoo/addons/fieldservice_maintenance/models/__init__.py
odoo/addons/fieldservice_maintenance/models/fsm_equipment.py
odoo/addons/fieldservice_maintenance/models/fsm_order.py
odoo/addons/fieldservice_maintenance/models/fsm_order_type.py
odoo/addons/fieldservice_maintenance/models/maintenance_equipment.py
odoo/addons/fieldservice_maintenance/models/maintenance_request.py
odoo/addons/fieldservice_maintenance/readme/CONFIGURE.rst
odoo/addons/fieldservice_maintenance/readme/CONTRIBUTORS.rst
odoo/addons/fieldservice_maintenance/readme/CREDITS.rst
odoo/addons/fieldservice_maintenance/readme/DESCRIPTION.rst
odoo/addons/fieldservice_maintenance/readme/INSTALL.rst
odoo/addons/fieldservice_maintenance/readme/ROADMAP.rst
odoo/addons/fieldservice_maintenance/readme/USAGE.rst
odoo/addons/fieldservice_maintenance/static/description/icon.png
odoo/addons/fieldservice_maintenance/static/description/index.html
odoo/addons/fieldservice_maintenance/tests/__init__.py
odoo/addons/fieldservice_maintenance/tests/test_fsm_maintenance.py
odoo/addons/fieldservice_maintenance/views/fsm_equipment_view.xml
odoo/addons/fieldservice_maintenance/views/fsm_order_view.xml
odoo/addons/fieldservice_maintenance/views/maintenance_equipment_view.xml
odoo/addons/fieldservice_maintenance/views/maintenance_request_view.xml
odoo12_addon_fieldservice_maintenance-12.0.1.2.1.dist-info/METADATA
odoo12_addon_fieldservice_maintenance-12.0.1.2.1.dist-info/WHEEL
odoo12_addon_fieldservice_maintenance-12.0.1.2.1.dist-info/top_level.txt
odoo12_addon_fieldservice_maintenance-12.0.1.2.1.dist-info/RECORD
